climind/__init__.py
climind/definitions.py
climind/config/__init__.py
climind/config/config.py
climind/config/dir_config.py
climind/data_manager/__init__.py
climind/data_manager/dataset_schema.json
climind/data_manager/metadata.py
climind/data_manager/metadata_schema.json
climind/data_manager/processing.py
climind/data_types/__init__.py
climind/data_types/grid.py
climind/data_types/timeseries.py
climind/data_types/jinja_templates/badc_boilerplate.jinja2
climind/fetchers/.env
climind/fetchers/__init__.py
climind/fetchers/fetcher_cds.py
climind/fetchers/fetcher_cmems_ftp.py
climind/fetchers/fetcher_ersst.py
climind/fetchers/fetcher_ftp.py
climind/fetchers/fetcher_grace.py
climind/fetchers/fetcher_jra55_grid.py
climind/fetchers/fetcher_no_url.py
climind/fetchers/fetcher_noaaglobaltemp.py
climind/fetchers/fetcher_promice.py
climind/fetchers/fetcher_standard_url.py
climind/fetchers/fetcher_url_with_backsearch.py
climind/fetchers/fetcher_utils.py
climind/metadata_files/Berkeley Earth_5x5.json
climind/metadata_files/ERA5_5x5.json
climind/metadata_files/GISTEMP_5x5.json
climind/metadata_files/HadCRUT5_5x5.json
climind/metadata_files/JRA-55_5x5.json
climind/metadata_files/NOAAGlobalTemp_5x5.json
climind/metadata_files/aviso.json
climind/metadata_files/aviso_ftp.json
climind/metadata_files/berkeley.json
climind/metadata_files/berkeley_ipcc.json
climind/metadata_files/berkeley_lsat.json
climind/metadata_files/cheng.json
climind/metadata_files/cheng2k.json
climind/metadata_files/clsat.json
climind/metadata_files/clsat_unrecon.json
climind/metadata_files/cmems_ph.json
climind/metadata_files/crutem5.json
climind/metadata_files/era5.json
climind/metadata_files/ersst.json
climind/metadata_files/gcos_ohc.json
climind/metadata_files/gcos_ohc_2k.json
climind/metadata_files/gistemp.json
climind/metadata_files/gml_n2o.json
climind/metadata_files/grace_antarctica.json
climind/metadata_files/grace_greenland.json
climind/metadata_files/hadcrut5.json
climind/metadata_files/hadsst4.json
Climind-0.1.dist-info/LICENSE
Climind-0.1.dist-info/METADATA
Climind-0.1.dist-info/WHEEL
Climind-0.1.dist-info/top_level.txt
Climind-0.1.dist-info/RECORD
