Metadata-Version: 2.1
Name: Climind
Version: 0.1
Summary: A python package for managing climate indicator information
Home-page: https://github.com/jjk-code-otter/climate-indicator-manager
Author: John Kennedy
Author-email: jjk.code.otter@gmail.com
License: GNU General Public License v3.0
License-File: LICENSE
Requires-Dist: pytest
Requires-Dist: numpy
Requires-Dist: requests
Requires-Dist: beautifulsoup4
Requires-Dist: pandas
Requires-Dist: jsonschema
Requires-Dist: matplotlib
Requires-Dist: seaborn
Requires-Dist: xarray
Requires-Dist: python-dotenv
Requires-Dist: regionmask
Requires-Dist: geopandas
Requires-Dist: shapely
Requires-Dist: cdsapi
Requires-Dist: cartopy
Requires-Dist: cftime
Requires-Dist: jinja2
Requires-Dist: python-docx
